{
	"name": "Pipeline 1",
	"properties": {
		"activities": [
			{
				"name": "Set variable1",
				"type": "SetVariable",
				"dependsOn": [],
				"policy": {
					"secureOutput": false,
					"secureInput": false
				},
				"userProperties": [],
				"typeProperties": {
					"variableName": "Test",
					"value": "abc"
				}
			}
		],
		"variables": {
			"Test": {
				"type": "String"
			}
		},
		"annotations": [],
		"lastPublishTime": "2024-03-04T15:59:50Z"
	},
	"type": "Microsoft.Synapse/workspaces/pipelines"
}